<annotation>
	<folder>imgs</folder>
	<filename>bill-gates.jpg</filename>
	<path>/home/tunghoang/PycharmProjects/image_classification/imgs/bill-gates.jpg</path>
	<source>
		<database>Unknown</database>
	</source>
	<size>
		<width>800</width>
		<height>533</height>
		<depth>3</depth>
	</size>
	<segmented>0</segmented>
	<object>
		<name>Bill Gates</name>
		<pose>Unspecified</pose>
		<truncated>0</truncated>
		<difficult>0</difficult>
		<bndbox>
			<xmin>164</xmin>
			<ymin>78</ymin>
			<xmax>443</xmax>
			<ymax>373</ymax>
		</bndbox>
	</object>
</annotation>
